LICENSE
MANIFEST.in
README.md
requirements-test.txt
requirements.txt
setup.cfg
setup.py
aiodockerpy/__init__.py
aiodockerpy/errors.py
aiodockerpy/version.py
aiodockerpy.egg-info/PKG-INFO
aiodockerpy.egg-info/SOURCES.txt
aiodockerpy.egg-info/dependency_links.txt
aiodockerpy.egg-info/not-zip-safe
aiodockerpy.egg-info/requires.txt
aiodockerpy.egg-info/top_level.txt
aiodockerpy/api/__init__.py
aiodockerpy/api/client.py
aiodockerpy/utils/__init__.py
aiodockerpy/utils/json_stream.py