Metadata-Version: 1.1
Name: aiodockerpy
Version: 0.6.1
Summary: aiohttp port of docker-py.
Home-page: https://github.com/tenforce/docker-py-aiohttp
Author: Cecile Tonglet
Author-email: cecile.tonglet@gmail.com
License: UNKNOWN
Platform: UNKNOWN
Classifier: Development Status :: 3 - Alpha
Classifier: Environment :: Other Environment
Classifier: Intended Audience :: Developers
Classifier: Operating System :: OS Independent
Classifier: Programming Language :: Python
Classifier: Programming Language :: Python :: 3 :: Only
Classifier: Programming Language :: Python :: 3.6
Classifier: Topic :: Utilities
Classifier: License :: OSI Approved :: Apache Software License
